qoqo_myqlm/__init__.py
qoqo_myqlm/backend/__init__.py
qoqo_myqlm/backend/myqlm_backend.py
qoqo_myqlm/backend/__pycache__/__init__.cpython-38.pyc
qoqo_myqlm/backend/__pycache__/myqlm_backend.cpython-38.pyc
qoqo_myqlm/interface/__init__.py
qoqo_myqlm/interface/myqlm_interface.py
qoqo_myqlm/interface/utilities.py
qoqo_myqlm-0.5.0.dist-info/licenses/LICENSE
qoqo_myqlm-0.5.0.dist-info/METADATA
qoqo_myqlm-0.5.0.dist-info/WHEEL
qoqo_myqlm-0.5.0.dist-info/top_level.txt
qoqo_myqlm-0.5.0.dist-info/RECORD
