Metadata-Version: 2.4
Name: qoqo_myqlm
Version: 0.5.0
Summary: An inteface to execute circuits from QOQO to MYQLM
Author-email: HQS Quantum Simulation GmbH <info@quantumsimulations.de>
Requires-Python: <3.14,>3.10
License-File: LICENSE
Requires-Dist: qoqo>=1.15
Requires-Dist: numpy
Requires-Dist: myqlm
Provides-Extra: tests
Requires-Dist: pytest-cov; extra == "tests"
Requires-Dist: pytest; extra == "tests"
Provides-Extra: dev
Requires-Dist: ruff; extra == "dev"
Requires-Dist: darglint; extra == "dev"
Requires-Dist: bandit; extra == "dev"
Requires-Dist: mypy; extra == "dev"
Requires-Dist: black; extra == "dev"
Provides-Extra: docs
Requires-Dist: pyyaml; extra == "docs"
Requires-Dist: sphinx>=2.1; extra == "docs"
Requires-Dist: nbsphinx; extra == "docs"
Requires-Dist: pygments; extra == "docs"
Requires-Dist: recommonmark; extra == "docs"
Requires-Dist: myst_parser; extra == "docs"
Requires-Dist: sphinx_rtd_theme; extra == "docs"
Requires-Dist: tomli; extra == "docs"
Dynamic: license-file
